pynbox/__init__.py
pynbox/assets/config.yaml
pynbox/config.py
pynbox/entrypoints/__init__.py
pynbox/entrypoints/cli.py
pynbox/exceptions.py
pynbox/model.py
pynbox/py.typed
pynbox/services.py
pynbox/version.py
pynbox/views.py
pynbox-0.5.1.dist-info/entry_points.txt
pynbox-0.5.1.dist-info/WHEEL
pynbox-0.5.1.dist-info/METADATA
pynbox-0.5.1.dist-info/license_files/LICENSE
pynbox-0.5.1.dist-info/RECORD
